crypto_bs/__init__.py
crypto_bs/black_scholes.py
crypto_bs/data_fetch.py
crypto_bs/greeks.py
crypto_bs/greeks_calculator.py
crypto_bs/models.py
crypto_bs/pricing.py
crypto_bs/utils.py
crypto_bs-0.1.0.dist-info/licenses/LICENSE
crypto_bs-0.1.0.dist-info/METADATA
crypto_bs-0.1.0.dist-info/WHEEL
crypto_bs-0.1.0.dist-info/top_level.txt
crypto_bs-0.1.0.dist-info/RECORD
