Metadata-Version: 2.4
Name: crypto_bs
Version: 0.1.0
Summary: Python library for pricing coin-settled crypto options
Author-email: Seyed Mohammad Hossein Fasihi <mhmd.fasihi@gmail.com>
License: MIT License
Project-URL: Homepage, https://github.com/MhmdFasihi/crypto_black_scholes
Project-URL: Repository, https://github.com/MhmdFasihi/crypto_black_scholes
Project-URL: Issues, https://github.com/MhmdFasihi/crypto_black_scholes/issues
Keywords: black-scholes,black-76,options,greeks,implied-volatility,crypto,bitcoin,deribit,pricing,risk
Classifier: License :: OSI Approved :: MIT License
Classifier: Programming Language :: Python :: 3
Classifier: Programming Language :: Python :: 3.10
Classifier: Programming Language :: Python :: 3.11
Classifier: Programming Language :: Python :: 3.12
Classifier: Intended Audience :: Financial and Insurance Industry
Classifier: Topic :: Office/Business :: Financial :: Investment
Classifier: Operating System :: OS Independent
Requires-Python: >=3.10
License-File: LICENSE
Requires-Dist: numpy>=1.21.0
Requires-Dist: scipy>=1.7.0
Requires-Dist: requests>=2.25.0
Requires-Dist: pandas>=1.3.0
Dynamic: license-file
